gym_rat_runner/__init__.py
gym_rat_runner/envs/__init__.py
gym_rat_runner/envs/maze_env.py
gym_rat_runner/envs/open_env.py
gym_rat_runner/envs/maze/Maze1.csv
gym_rat_runner/envs/maze/Open_Maze.csv
gym_rat_runner/images/cat.png
gym_rat_runner/images/cheese.png
gym_rat_runner/images/rat.png
gym_rat_runner/images/wall.png
gym_rat_runner-0.1.6.dist-info/LICENSE
gym_rat_runner-0.1.6.dist-info/METADATA
gym_rat_runner-0.1.6.dist-info/WHEEL
gym_rat_runner-0.1.6.dist-info/top_level.txt
gym_rat_runner-0.1.6.dist-info/RECORD
